langchain_logger/callback.py
langchain_logger/logger.py
langchain_logger-0.1.0.dist-info/LICENSE.md
langchain_logger-0.1.0.dist-info/METADATA
langchain_logger-0.1.0.dist-info/WHEEL
langchain_logger-0.1.0.dist-info/RECORD
