Metadata-Version: 2.1
Name: langchain-logger
Version: 0.1.0
Summary: A Chain of Thought logger for langchain
Home-page: https://github.com/thevgergroup/langchain-logger
License: MIT
Keywords: langchain,logger,chain of thought,AI,GenAI
Author: patrick o'leary
Author-email: pjaol@pjaol.com
Requires-Python: >=3.11,<4.0
Classifier: License :: OSI Approved :: MIT License
Classifier: Programming Language :: Python :: 3
Classifier: Programming Language :: Python :: 3.11
Classifier: Programming Language :: Python :: 3.12
Classifier: Topic :: Scientific/Engineering :: Artificial Intelligence
Classifier: Topic :: System :: Logging
Requires-Dist: langchain (>=0.1.12,<0.2.0)
Requires-Dist: langchain-core (>=0.1.31,<0.2.0)
Project-URL: Documentation, https://github.com/thevgergroup/langchain-logger
Project-URL: Repository, https://github.com/thevgergroup/langchain-logger.git
